{"lastUpdated":"2026-06-17T12:04:19Z","indices":[{"symbol":"^GSPC","regularMarketPrice":7511.35,"regularMarketChange":-42.94,"regularMarketChangePercent":-0.57,"name":"S&P 500"},{"symbol":"^DJI","regularMarketPrice":51999.67,"regularMarketChange":328.64,"regularMarketChangePercent":0.64,"name":"Dow Jones"},{"symbol":"^IXIC","regularMarketPrice":26376.34,"regularMarketChange":-307.6,"regularMarketChangePercent":-1.15,"name":"NASDAQ"},{"symbol":"^RUT","regularMarketPrice":2939.2,"regularMarketChange":-25.89,"regularMarketChangePercent":-0.87,"name":"Russell 2000"}]}